bib2.py
bib2-1.6.1.dist-info/METADATA
bib2-1.6.1.dist-info/WHEEL
bib2-1.6.1.dist-info/entry_points.txt
bib2-1.6.1.dist-info/RECORD
