Metadata-Version: 2.4
Name: bib2
Version: 1.6.1
Summary: A simple converter of MARC/MARCXML/PICAXML to CSV/TSV/parquet
Project-URL: repository, https://github.com/hsci-r/bibxml2
Author-email: Eetu Mäkelä <eetu.makela@helsinki.fi>
License-Expression: MIT
Keywords: MARC,MARCXML,PICA XML,bibliographic data,data conversion
Requires-Python: >=3.9
Requires-Dist: click>=8.0.0
Requires-Dist: duckdb>=1.3.2
Requires-Dist: fsspec>=2025.2.0
Requires-Dist: hsciutil>=0.1.2
Requires-Dist: lxml>=5.0.0
Requires-Dist: pyarrow>=20.0.0
Requires-Dist: pymarc>=5.3.1
Requires-Dist: s3fs>=2025.2.0
Requires-Dist: tqdm>=4.5.0
Requires-Dist: zstandard>=0.23.0
